whitespacesv/__init__.py
whitespacesv/document.py
whitespacesv/line.py
whitespacesv/parser.py
whitespacesv/serializer.py
whitespacesv/txt.py
whitespacesv/utils.py
whitespacesv-0.1.0.dist-info/licenses/LICENSE
whitespacesv-0.1.0.dist-info/METADATA
whitespacesv-0.1.0.dist-info/WHEEL
whitespacesv-0.1.0.dist-info/top_level.txt
whitespacesv-0.1.0.dist-info/RECORD
